Metadata-Version: 2.4
Name: grepsr-cli
Version: 0.9.54
Summary: A Cli tool for Grepsr Developers
Home-page: https://bitbucket.org/grepsr/grepsr-cli/
Author: grepsr
Author-email: dev@grepsr.com
License: unlicensed
License-File: LICENSE.md
Requires-Dist: cement>=3.0.4
Requires-Dist: Jinja2>=2.11.3
Requires-Dist: PyYAML==6.0.1
Requires-Dist: colorlog>=4.8.0
Requires-Dist: semver>=2.13.0
Requires-Dist: terminaltables>=3.1.0
Requires-Dist: requests>=2.25.1
Requires-Dist: boto3<2.0.0,>=1.9.0
Dynamic: author
Dynamic: author-email
Dynamic: description
Dynamic: description-content-type
Dynamic: home-page
Dynamic: license
Dynamic: license-file
Dynamic: requires-dist
Dynamic: summary
